[
  {
    "slug": "desaparecidos-terremoto-venezuela",
    "section": "missing",
    "name": "Desaparecidos Terremoto Venezuela",
    "url": "https://desaparecidosterremotovenezuela.com/",
    "category": "website",
    "purpose": "report-and-search",
    "coverage": "national",
    "language": "es",
    "requires_login": false,
    "last_checked_at": "2026-06-26",
    "owner": "Volunteer initiative",
    "operator_type": "volunteer",
    "status": "active",
    "crawler_priority": 1,
    "accepts_new_reports": true,
    "public_search": true,
    "report_found": true,
    "public_contact": null,
    "services": [
      "missing-report",
      "missing-search",
      "found-report"
    ],
    "report_stats": {
      "reported": 62161,
      "found": 9991,
      "as_of": "2026-06-26",
      "source": "self-reported"
    },
    "summary": "Registro ciudadano para reportar y buscar personas desaparecidas tras el terremoto. Se ha citado como una de las plataformas públicas más referenciadas.",
    "use_when": {
      "es": "Úsalo si buscas o quieres reportar a una persona desaparecida.",
      "en": "Use this to search for or report a missing person."
    },
    "notes": [
      "La URL cargó correctamente durante la revisión de enlaces del 26 de junio de 2026.",
      "Está orientado a reportar personas desaparecidas, buscar registros y marcar a alguien como encontrado."
    ],
    "tags": [
      "terremoto",
      "personas-desaparecidas",
      "registro-publico",
      "gestion-voluntaria"
    ],
    "use_when_label": "Úsalo si buscas o quieres reportar a una persona desaparecida.",
    "warning_label": "",
    "category_label": "Sitio web",
    "purpose_label": "Reportar y buscar",
    "status_label": "Activa",
    "operator_type_label": "Voluntario",
    "coverage_label": "Nacional",
    "language_label": "Español",
    "requires_login_label": "No",
    "accepts_reports_label_value": "Sí",
    "public_search_label_value": "Sí",
    "report_found_label_value": "Sí",
    "owner_label": "Iniciativa voluntaria",
    "service_labels": [
      "Reportar desaparecidos",
      "Buscar personas",
      "Reportar encontrado / a salvo"
    ],
    "last_checked_label": "2026-06-26",
    "public_contact_label": "No revisado",
    "api_url_label": "No revisado",
    "source_code_url_label": "No revisado"
  },
  {
    "slug": "venezuela-te-busca",
    "section": "missing",
    "name": "Venezuela Te Busca",
    "url": "https://venezuelatebusca.com/",
    "category": "website",
    "purpose": "report-and-search",
    "coverage": "national",
    "language": "es",
    "requires_login": false,
    "last_checked_at": "2026-06-26",
    "owner": "Volunteer initiative",
    "operator_type": "volunteer",
    "status": "active",
    "crawler_priority": 1,
    "accepts_new_reports": true,
    "public_search": true,
    "report_found": true,
    "public_contact": null,
    "services": [
      "missing-report",
      "missing-search",
      "found-report"
    ],
    "summary": "Registro colaborativo de personas desaparecidas con flujos de búsqueda y reporte.",
    "use_when": {
      "es": "Úsalo si buscas o quieres reportar a una persona desaparecida.",
      "en": "Use this to search for or report a missing person."
    },
    "notes": [
      "La URL cargó correctamente durante la revisión de enlaces del 26 de junio de 2026.",
      "Se reporta que permite buscar por nombre, cédula o ubicación."
    ],
    "tags": [
      "terremoto",
      "personas-desaparecidas",
      "busqueda",
      "registro"
    ],
    "report_stats": {
      "reported": 32169,
      "found": 7730,
      "as_of": "2026-06-26T21:19:07.263Z",
      "source": "self-reported"
    },
    "use_when_label": "Úsalo si buscas o quieres reportar a una persona desaparecida.",
    "warning_label": "",
    "category_label": "Sitio web",
    "purpose_label": "Reportar y buscar",
    "status_label": "Activa",
    "operator_type_label": "Voluntario",
    "coverage_label": "Nacional",
    "language_label": "Español",
    "requires_login_label": "No",
    "accepts_reports_label_value": "Sí",
    "public_search_label_value": "Sí",
    "report_found_label_value": "Sí",
    "owner_label": "Iniciativa voluntaria",
    "service_labels": [
      "Reportar desaparecidos",
      "Buscar personas",
      "Reportar encontrado / a salvo"
    ],
    "last_checked_label": "2026-06-26",
    "public_contact_label": "No revisado",
    "api_url_label": "No revisado",
    "source_code_url_label": "No revisado"
  },
  {
    "slug": "venezuela-reporta",
    "section": "missing",
    "name": "Venezuela Reporta",
    "url": "https://venezuelareporta.org/",
    "category": "website",
    "purpose": "report-and-search",
    "coverage": "national",
    "language": "es",
    "requires_login": false,
    "last_checked_at": "2026-06-26",
    "owner": "Citizen platform",
    "operator_type": "citizen",
    "status": "active",
    "crawler_priority": 2,
    "accepts_new_reports": true,
    "public_search": true,
    "report_found": true,
    "public_contact": null,
    "services": [
      "missing-report",
      "missing-search",
      "found-report"
    ],
    "report_stats": {
      "reported": 71201,
      "found": 6014,
      "as_of": "2026-06-26T21:19:07.263Z",
      "source": "self-reported"
    },
    "summary": "Plataforma ciudadana para reportar, buscar y marcar personas desaparecidas como encontradas tras el terremoto.",
    "use_when": {
      "es": "Úsalo si buscas o quieres reportar a una persona desaparecida.",
      "en": "Use this to search for or report a missing person."
    },
    "notes": [
      "La URL cargó correctamente durante la revisión de enlaces del 26 de junio de 2026.",
      "La navegación pública visible muestra flujos de búsqueda, reporte y marcado de encontrado."
    ],
    "tags": [
      "terremoto",
      "personas-desaparecidas",
      "emergencia",
      "plataforma-ciudadana"
    ],
    "use_when_label": "Úsalo si buscas o quieres reportar a una persona desaparecida.",
    "warning_label": "",
    "category_label": "Sitio web",
    "purpose_label": "Reportar y buscar",
    "status_label": "Activa",
    "operator_type_label": "Ciudadano",
    "coverage_label": "Nacional",
    "language_label": "Español",
    "requires_login_label": "No",
    "accepts_reports_label_value": "Sí",
    "public_search_label_value": "Sí",
    "report_found_label_value": "Sí",
    "owner_label": "Plataforma ciudadana",
    "service_labels": [
      "Reportar desaparecidos",
      "Buscar personas",
      "Reportar encontrado / a salvo"
    ],
    "last_checked_label": "2026-06-26",
    "public_contact_label": "No revisado",
    "api_url_label": "No revisado",
    "source_code_url_label": "No revisado"
  },
  {
    "slug": "red-ayuda-venezuela",
    "section": "missing",
    "name": "Red Ayuda Venezuela",
    "url": "https://redayudavenezuela.com/",
    "category": "website",
    "purpose": "report-and-search",
    "coverage": "national",
    "language": "es",
    "requires_login": false,
    "last_checked_at": "2026-06-26",
    "owner": "Citizen platform",
    "operator_type": "citizen",
    "status": "active",
    "crawler_priority": 1,
    "accepts_new_reports": true,
    "public_search": true,
    "report_found": true,
    "public_contact": null,
    "services": [
      "missing-report",
      "missing-search",
      "safe-checkin"
    ],
    "summary": "Plataforma ciudadana de emergencia para avisar que una persona está a salvo, buscar personas y coordinar ayuda tras el terremoto.",
    "use_when": {
      "es": "Úsalo si quieres avisar que alguien está a salvo o buscar a una persona.",
      "en": "Use this to mark someone safe or search for a person."
    },
    "notes": [
      "La URL cargó correctamente durante la revisión de enlaces del 26 de junio de 2026.",
      "El sitio se describe como una red ciudadana de emergencia para reportes de estado, búsqueda de personas y coordinación de ayuda."
    ],
    "tags": [
      "terremoto",
      "personas-desaparecidas",
      "emergencia",
      "plataforma-ciudadana",
      "reporte"
    ],
    "use_when_label": "Úsalo si quieres avisar que alguien está a salvo o buscar a una persona.",
    "warning_label": "",
    "category_label": "Sitio web",
    "purpose_label": "Reportar y buscar",
    "status_label": "Activa",
    "operator_type_label": "Ciudadano",
    "coverage_label": "Nacional",
    "language_label": "Español",
    "requires_login_label": "No",
    "accepts_reports_label_value": "Sí",
    "public_search_label_value": "Sí",
    "report_found_label_value": "Sí",
    "owner_label": "Plataforma ciudadana",
    "service_labels": [
      "Reportar desaparecidos",
      "Buscar personas",
      "Avisar que alguien está a salvo"
    ],
    "last_checked_label": "2026-06-26",
    "public_contact_label": "No revisado",
    "api_url_label": "No revisado",
    "source_code_url_label": "No revisado"
  },
  {
    "slug": "localizados-venezuela",
    "section": "located",
    "name": "Localizados Venezuela",
    "url": "https://localizadosvenezuela.com/",
    "api_url": "https://localizadosvenezuela.com/api",
    "source_code_url": "https://github.com/ggangix/localizados-venezuela",
    "category": "website",
    "purpose": "located-people",
    "coverage": "national",
    "language": "es",
    "requires_login": false,
    "last_checked_at": "2026-06-26",
    "owner": "Volunteer initiative",
    "operator_type": "volunteer",
    "status": "active",
    "crawler_priority": 1,
    "accepts_new_reports": true,
    "public_search": true,
    "report_found": false,
    "public_contact": null,
    "services": [
      "located-search",
      "located-report"
    ],
    "report_stats": {
      "located": 1997,
      "as_of": "2026-06-26",
      "source": "self-reported"
    },
    "summary": "Plataforma pública y de código abierto que consolida listados de pacientes en hospitales para ayudar a ubicar a personas ya localizadas tras el terremoto. Incluye API pública de solo lectura.",
    "use_when": {
      "es": "Úsalo para buscar a una persona en los listados de pacientes de hospitales.",
      "en": "Use this to search for a person in hospital patient listings."
    },
    "warning": {
      "es": "Reúne listados de pacientes en hospitales, no reportes de desaparecidos. Si buscas a alguien desaparecido, usa la sección Personas desaparecidas.",
      "en": "It gathers hospital patient listings, not missing-person reports. To search for someone missing, use the Missing people section."
    },
    "notes": [
      "La documentación de la API pública está disponible en /api y los endpoints GET de la v1 responden JSON con CORS habilitado para lectura.",
      "El proyecto aclara que es solo para personas localizadas y redirige los casos de desaparecidos a desaparecidosterremotovenezuela.com."
    ],
    "tags": [
      "terremoto",
      "personas-desaparecidas",
      "codigo-abierto",
      "api",
      "hospitales"
    ],
    "use_when_label": "Úsalo para buscar a una persona en los listados de pacientes de hospitales.",
    "warning_label": "Reúne listados de pacientes en hospitales, no reportes de desaparecidos. Si buscas a alguien desaparecido, usa la sección Personas desaparecidas.",
    "category_label": "Sitio web",
    "purpose_label": "Personas localizadas",
    "status_label": "Activa",
    "operator_type_label": "Voluntario",
    "coverage_label": "Nacional",
    "language_label": "Español",
    "requires_login_label": "No",
    "accepts_reports_label_value": "Sí",
    "public_search_label_value": "Sí",
    "report_found_label_value": "No",
    "owner_label": "Iniciativa voluntaria",
    "service_labels": [
      "Buscar personas localizadas",
      "Aportar personas localizadas"
    ],
    "last_checked_label": "2026-06-26",
    "public_contact_label": "No revisado",
    "api_url_label": "https://localizadosvenezuela.com/api",
    "source_code_url_label": "https://github.com/ggangix/localizados-venezuela"
  },
  {
    "slug": "hospitales-en-venezuela",
    "section": "located",
    "name": "Hospitales en Venezuela",
    "url": "https://hospitalesenvenezuela.com/",
    "category": "website",
    "purpose": "located-people",
    "coverage": "national",
    "language": "es",
    "requires_login": false,
    "last_checked_at": "2026-06-26",
    "owner": "Volunteer initiative",
    "operator_type": "volunteer",
    "status": "active",
    "crawler_priority": 2,
    "accepts_new_reports": null,
    "public_search": true,
    "report_found": false,
    "public_contact": null,
    "services": [
      "located-search",
      "hospitals"
    ],
    "summary": "Directory to find a relative admitted to hospitals and health centers in Venezuela after the earthquake.",
    "use_when": {
      "es": "Úsalo para buscar a un familiar ingresado en un hospital o centro de salud.",
      "en": "Use this to find a relative admitted to a hospital or health center."
    },
    "warning": {
      "es": "Reúne listados de pacientes en hospitales, no reportes de desaparecidos. Si buscas a alguien que no está hospitalizado, usa la sección Personas desaparecidas.",
      "en": "It gathers hospital patient listings, not missing-person reports. If the person is not hospitalized, use the Missing people section."
    },
    "notes": [
      "URL loaded successfully during the June 26, 2026 link check.",
      "The site explicitly redirects non-hospitalized missing-person cases to redayudavenezuela.com."
    ],
    "tags": [
      "terremoto",
      "hospitales",
      "busqueda"
    ],
    "use_when_label": "Úsalo para buscar a un familiar ingresado en un hospital o centro de salud.",
    "warning_label": "Reúne listados de pacientes en hospitales, no reportes de desaparecidos. Si buscas a alguien que no está hospitalizado, usa la sección Personas desaparecidas.",
    "category_label": "Sitio web",
    "purpose_label": "Personas localizadas",
    "status_label": "Activa",
    "operator_type_label": "Voluntario",
    "coverage_label": "Nacional",
    "language_label": "Español",
    "requires_login_label": "No",
    "accepts_reports_label_value": "No revisado",
    "public_search_label_value": "Sí",
    "report_found_label_value": "No",
    "owner_label": "Iniciativa voluntaria",
    "service_labels": [
      "Buscar personas localizadas",
      "Hospitales"
    ],
    "last_checked_label": "2026-06-26",
    "public_contact_label": "No revisado",
    "api_url_label": "No revisado",
    "source_code_url_label": "No revisado"
  },
  {
    "slug": "asistencia-medica-fvivemas",
    "section": "located",
    "name": "Asistencia Médica Fvivemas",
    "url": "https://asistencia-medica-fvivemas.web.app/",
    "category": "website",
    "purpose": "located-people",
    "coverage": "national",
    "language": "es",
    "requires_login": false,
    "last_checked_at": "2026-06-26",
    "owner": "Volunteer initiative",
    "operator_type": "volunteer",
    "status": "active",
    "crawler_priority": 2,
    "accepts_new_reports": true,
    "public_search": true,
    "report_found": false,
    "public_contact": null,
    "services": [
      "located-search",
      "located-report"
    ],
    "summary": "Solidarity platform built by medical students from Fundación Vive Más to search for hospitalized patients and report medical emergencies after the earthquake.",
    "use_when": {
      "es": "Úsalo para buscar pacientes hospitalizados o reportar una emergencia médica.",
      "en": "Use this to search for hospitalized patients or report a medical emergency."
    },
    "warning": {
      "es": "Se enfoca en pacientes hospitalizados y emergencias médicas, no en reportes de desaparecidos. Si buscas a una persona desaparecida, usa la sección Personas desaparecidas.",
      "en": "It focuses on hospitalized patients and medical emergencies, not missing-person reports. To search for a missing person, use the Missing people section."
    },
    "notes": [
      "URL loaded successfully during the June 26, 2026 link check.",
      "Built by medical students who are members of Fundación Vive Más."
    ],
    "tags": [
      "terremoto",
      "hospitales",
      "medical",
      "gestion-voluntaria"
    ],
    "use_when_label": "Úsalo para buscar pacientes hospitalizados o reportar una emergencia médica.",
    "warning_label": "Se enfoca en pacientes hospitalizados y emergencias médicas, no en reportes de desaparecidos. Si buscas a una persona desaparecida, usa la sección Personas desaparecidas.",
    "category_label": "Sitio web",
    "purpose_label": "Personas localizadas",
    "status_label": "Activa",
    "operator_type_label": "Voluntario",
    "coverage_label": "Nacional",
    "language_label": "Español",
    "requires_login_label": "No",
    "accepts_reports_label_value": "Sí",
    "public_search_label_value": "Sí",
    "report_found_label_value": "No",
    "owner_label": "Iniciativa voluntaria",
    "service_labels": [
      "Buscar personas localizadas",
      "Aportar personas localizadas"
    ],
    "last_checked_label": "2026-06-26",
    "public_contact_label": "No revisado",
    "api_url_label": "No revisado",
    "source_code_url_label": "No revisado"
  },
  {
    "slug": "siviv",
    "section": "located",
    "name": "SIVIV — Sistema de Información de Víctimas",
    "url": "https://siviv.pages.dev/",
    "category": "website",
    "purpose": "located-people",
    "coverage": "national",
    "language": "es",
    "requires_login": false,
    "last_checked_at": "2026-06-26",
    "owner": "Volunteer initiative",
    "operator_type": "volunteer",
    "status": "active",
    "crawler_priority": 3,
    "accepts_new_reports": false,
    "public_search": true,
    "report_found": false,
    "public_contact": null,
    "services": [
      "located-search"
    ],
    "summary": "Search tool for people affected by the earthquake, to find relatives admitted to health and care centers.",
    "use_when": {
      "es": "Úsalo para buscar a un familiar en los centros de atención.",
      "en": "Use this to search for a relative in care centers."
    },
    "warning": {
      "es": "Reúne listados de personas en centros de atención, no reportes de desaparecidos. Si buscas a alguien que no está en un centro de salud, usa la sección Personas desaparecidas.",
      "en": "It gathers listings of people in care centers, not missing-person reports. If the person is not in a health center, use the Missing people section."
    },
    "notes": [
      "URL loaded successfully during the June 26, 2026 link check.",
      "Hosted on a free static host (pages.dev); confirm it is still online before relying on it."
    ],
    "tags": [
      "terremoto",
      "hospitales",
      "busqueda",
      "gestion-voluntaria"
    ],
    "use_when_label": "Úsalo para buscar a un familiar en los centros de atención.",
    "warning_label": "Reúne listados de personas en centros de atención, no reportes de desaparecidos. Si buscas a alguien que no está en un centro de salud, usa la sección Personas desaparecidas.",
    "category_label": "Sitio web",
    "purpose_label": "Personas localizadas",
    "status_label": "Activa",
    "operator_type_label": "Voluntario",
    "coverage_label": "Nacional",
    "language_label": "Español",
    "requires_login_label": "No",
    "accepts_reports_label_value": "No",
    "public_search_label_value": "Sí",
    "report_found_label_value": "No",
    "owner_label": "Iniciativa voluntaria",
    "service_labels": [
      "Buscar personas localizadas"
    ],
    "last_checked_label": "2026-06-26",
    "public_contact_label": "No revisado",
    "api_url_label": "No revisado",
    "source_code_url_label": "No revisado"
  },
  {
    "slug": "venezuela-resiste-terremotove",
    "section": "missing",
    "name": "Venezuela Resiste (TerremotoVE)",
    "url": "https://terremotove.netlify.app/",
    "category": "map",
    "purpose": "report-and-search",
    "coverage": "national",
    "language": "es",
    "requires_login": false,
    "last_checked_at": "2026-06-26",
    "owner": "Acceso Libre",
    "operator_type": "citizen",
    "status": "active",
    "crawler_priority": 2,
    "accepts_new_reports": true,
    "public_search": true,
    "report_found": false,
    "public_contact": null,
    "services": [
      "missing-report",
      "missing-search",
      "damage-reports"
    ],
    "summary": "Mapa colaborativo de Acceso Libre para reportar edificios colapsados y personas desaparecidas, sobre todo en Yaracuy, y coordinar búsqueda y rescate.",
    "use_when": {
      "es": "Úsalo si quieres reportar o ubicar personas desaparecidas y edificios colapsados en el mapa.",
      "en": "Use this to report or locate missing people and collapsed buildings on the map."
    },
    "notes": [
      "La URL cargó correctamente durante la revisión de enlaces del 26 de junio de 2026.",
      "Mapa ciudadano abierto; los reportes no están verificados de forma independiente y se invitan correcciones públicas."
    ],
    "tags": [
      "terremoto",
      "personas-desaparecidas",
      "mapa",
      "danos",
      "comunidad"
    ],
    "use_when_label": "Úsalo si quieres reportar o ubicar personas desaparecidas y edificios colapsados en el mapa.",
    "warning_label": "",
    "category_label": "Mapa",
    "purpose_label": "Reportar y buscar",
    "status_label": "Activa",
    "operator_type_label": "Ciudadano",
    "coverage_label": "Nacional",
    "language_label": "Español",
    "requires_login_label": "No",
    "accepts_reports_label_value": "Sí",
    "public_search_label_value": "Sí",
    "report_found_label_value": "No",
    "owner_label": "Acceso Libre",
    "service_labels": [
      "Reportar desaparecidos",
      "Buscar personas",
      "Reportes de daños"
    ],
    "last_checked_label": "2026-06-26",
    "public_contact_label": "No revisado",
    "api_url_label": "No revisado",
    "source_code_url_label": "No revisado"
  },
  {
    "slug": "enlaza-venezuela",
    "section": "aid",
    "name": "Enlaza Venezuela",
    "url": "https://www.enlazavenezuela.com/",
    "category": "website",
    "purpose": "aid-and-updates",
    "coverage": "national",
    "language": "es",
    "requires_login": false,
    "last_checked_at": "2026-06-26",
    "owner": "Community responders",
    "operator_type": "community",
    "status": "active",
    "crawler_priority": 3,
    "accepts_new_reports": true,
    "public_search": true,
    "report_found": false,
    "public_contact": null,
    "services": [
      "aid-resources",
      "shelters",
      "situation-updates"
    ],
    "summary": "Plataforma comunitaria que conecta a quienes necesitan rescate, refugio, comida o transporte con voluntarios a través de WhatsApp, con estados de \"voy en camino\" y \"rescatados\".",
    "use_when": {
      "es": "Úsalo si necesitas o puedes ofrecer ayuda: rescate, refugio, comida o transporte.",
      "en": "Use this if you need or can offer help: rescue, shelter, food, or transport."
    },
    "notes": [
      "La URL cargó correctamente durante la revisión de enlaces del 26 de junio de 2026.",
      "Coordina solicitudes y ofertas de ayuda; no es una herramienta de búsqueda de personas ni de restablecimiento de contacto."
    ],
    "tags": [
      "terremoto",
      "emergencia",
      "ayuda",
      "comunidad",
      "rescate"
    ],
    "use_when_label": "Úsalo si necesitas o puedes ofrecer ayuda: rescate, refugio, comida o transporte.",
    "warning_label": "",
    "category_label": "Sitio web",
    "purpose_label": "Ayuda y actualizaciones",
    "status_label": "Activa",
    "operator_type_label": "Comunitario",
    "coverage_label": "Nacional",
    "language_label": "Español",
    "requires_login_label": "No",
    "accepts_reports_label_value": "Sí",
    "public_search_label_value": "Sí",
    "report_found_label_value": "No",
    "owner_label": "Respondedores comunitarios",
    "service_labels": [
      "Recursos de ayuda",
      "Refugios",
      "Actualizaciones de situación"
    ],
    "last_checked_label": "2026-06-26",
    "public_contact_label": "No revisado",
    "api_url_label": "No revisado",
    "source_code_url_label": "No revisado"
  },
  {
    "slug": "yummy-sos",
    "section": "aid",
    "name": "Yummy SOS",
    "url": "https://sos.yummyrides.com/",
    "category": "website",
    "purpose": "aid-and-updates",
    "coverage": "national",
    "language": "es",
    "requires_login": false,
    "last_checked_at": "2026-06-26",
    "owner": "Company platform",
    "operator_type": "company",
    "status": "active",
    "crawler_priority": 3,
    "accepts_new_reports": true,
    "public_search": true,
    "report_found": false,
    "public_contact": null,
    "services": [
      "damage-reports",
      "shelters",
      "aid-resources"
    ],
    "summary": "Sitio de emergencia operado por Yummy para reportar daños estructurales, ver reportes públicos y encontrar refugios tras el terremoto.",
    "use_when": {
      "es": "Úsalo para reportar o consultar daños estructurales y encontrar refugios y recursos de emergencia.",
      "en": "Use this to report or check structural damage and find shelters and emergency resources."
    },
    "notes": [
      "La URL cargó correctamente durante la revisión de enlaces del 26 de junio de 2026.",
      "Los metadatos de la página y la navegación visible muestran flujos públicos para reportar daños, ver reportes, refugios y recursos."
    ],
    "tags": [
      "terremoto",
      "emergencia",
      "danos",
      "refugio",
      "company"
    ],
    "use_when_label": "Úsalo para reportar o consultar daños estructurales y encontrar refugios y recursos de emergencia.",
    "warning_label": "",
    "category_label": "Sitio web",
    "purpose_label": "Ayuda y actualizaciones",
    "status_label": "Activa",
    "operator_type_label": "Empresa",
    "coverage_label": "Nacional",
    "language_label": "Español",
    "requires_login_label": "No",
    "accepts_reports_label_value": "Sí",
    "public_search_label_value": "Sí",
    "report_found_label_value": "No",
    "owner_label": "Plataforma empresarial",
    "service_labels": [
      "Reportes de daños",
      "Refugios",
      "Recursos de ayuda"
    ],
    "last_checked_label": "2026-06-26",
    "public_contact_label": "No revisado",
    "api_url_label": "No revisado",
    "source_code_url_label": "No revisado"
  },
  {
    "slug": "ayuda-venezuela-2026",
    "section": "aid",
    "name": "Ayuda Venezuela 2026",
    "url": "https://ayudavenezuela2026.com/",
    "category": "website",
    "purpose": "aid-and-updates",
    "coverage": "national",
    "language": "es",
    "requires_login": null,
    "last_checked_at": "2026-06-26",
    "owner": "Unknown",
    "operator_type": "unknown",
    "status": "monitor",
    "crawler_priority": 3,
    "accepts_new_reports": null,
    "public_search": null,
    "report_found": null,
    "public_contact": null,
    "services": [
      "aid-resources"
    ],
    "summary": "Plataforma de ayuda relacionada con el terremoto de Venezuela de 2026. Sus capacidades aún no están verificadas.",
    "use_when": {
      "es": "Úsalo como vía adicional de ayuda; verifica primero porque aún no está confirmada.",
      "en": "Use this as an additional aid channel; verify first, as it is not yet confirmed."
    },
    "warning": {
      "es": "Aún no verificado. La revisión automática fue bloqueada (403); confirma el sitio antes de confiar en él.",
      "en": "Not yet verified. The automated check was blocked (403); confirm the site before relying on it."
    },
    "notes": [
      "La revisión automática de enlaces devolvió HTTP 403 el 26 de junio de 2026, así que la disponibilidad y las capacidades deben verificarse manualmente.",
      "Se incluye de forma provisional como recurso de ayuda, pendiente de revisión manual."
    ],
    "tags": [
      "terremoto",
      "emergencia",
      "ayuda"
    ],
    "use_when_label": "Úsalo como vía adicional de ayuda; verifica primero porque aún no está confirmada.",
    "warning_label": "Aún no verificado. La revisión automática fue bloqueada (403); confirma el sitio antes de confiar en él.",
    "category_label": "Sitio web",
    "purpose_label": "Ayuda y actualizaciones",
    "status_label": "Verificar manualmente",
    "operator_type_label": "No verificado",
    "coverage_label": "Nacional",
    "language_label": "Español",
    "requires_login_label": "No revisado",
    "accepts_reports_label_value": "No revisado",
    "public_search_label_value": "No revisado",
    "report_found_label_value": "No revisado",
    "owner_label": "Desconocido",
    "service_labels": [
      "Recursos de ayuda"
    ],
    "last_checked_label": "2026-06-26",
    "public_contact_label": "No revisado",
    "api_url_label": "No revisado",
    "source_code_url_label": "No revisado"
  },
  {
    "slug": "punto-de-apoyo-venezuela",
    "section": "aid",
    "name": "Punto de Apoyo Venezuela",
    "url": "https://www.puntodeapoyovenezuela.com/",
    "category": "map",
    "purpose": "aid-and-updates",
    "coverage": "national",
    "language": "es",
    "requires_login": false,
    "last_checked_at": "2026-06-26",
    "owner": "Citizen platform",
    "operator_type": "citizen",
    "status": "active",
    "crawler_priority": 2,
    "accepts_new_reports": true,
    "public_search": true,
    "report_found": false,
    "public_contact": null,
    "services": [
      "aid-resources",
      "shelters",
      "situation-updates"
    ],
    "summary": "Collaborative non-profit emergency map where people mark and find nearby resources — collection centers, mutual aid, shelters, hospitals, WiFi, and power — to request or offer help.",
    "use_when": {
      "es": "Úsalo para marcar o encontrar recursos cercanos: acopios, refugios, hospitales, WiFi o energía.",
      "en": "Use this to mark or find nearby resources: collection centers, shelters, hospitals, WiFi, or power."
    },
    "notes": [
      "URL loaded successfully during the June 26, 2026 link check.",
      "Built by Valentín Fuentes (X: @VxlentinF); markers can both request and offer help."
    ],
    "tags": [
      "terremoto",
      "emergencia",
      "ayuda",
      "mapa",
      "comunidad"
    ],
    "use_when_label": "Úsalo para marcar o encontrar recursos cercanos: acopios, refugios, hospitales, WiFi o energía.",
    "warning_label": "",
    "category_label": "Mapa",
    "purpose_label": "Ayuda y actualizaciones",
    "status_label": "Activa",
    "operator_type_label": "Ciudadano",
    "coverage_label": "Nacional",
    "language_label": "Español",
    "requires_login_label": "No",
    "accepts_reports_label_value": "Sí",
    "public_search_label_value": "Sí",
    "report_found_label_value": "No",
    "owner_label": "Plataforma ciudadana",
    "service_labels": [
      "Recursos de ayuda",
      "Refugios",
      "Actualizaciones de situación"
    ],
    "last_checked_label": "2026-06-26",
    "public_contact_label": "No revisado",
    "api_url_label": "No revisado",
    "source_code_url_label": "No revisado"
  },
  {
    "slug": "acopiove",
    "section": "aid",
    "name": "AcopioVE",
    "url": "https://acopiove.org/",
    "category": "map",
    "purpose": "aid-and-updates",
    "coverage": "national",
    "language": "es",
    "requires_login": false,
    "last_checked_at": "2026-06-26",
    "owner": "Volunteer initiative",
    "operator_type": "volunteer",
    "status": "active",
    "crawler_priority": 2,
    "accepts_new_reports": true,
    "public_search": true,
    "report_found": false,
    "public_contact": null,
    "services": [
      "aid-resources"
    ],
    "summary": "Interactive map of 350+ collection centers across Venezuela and the diaspora (16 countries) showing where to drop off food, medicine, clothing, and water. Updated in real time.",
    "use_when": {
      "es": "Úsalo para encontrar el centro de acopio más cercano donde llevar alimentos, medicinas, ropa o agua.",
      "en": "Use this to find the nearest collection center to drop off food, medicine, clothing, or water."
    },
    "notes": [
      "URL loaded successfully during the June 26, 2026 link check.",
      "Covers collection centers in Venezuela, Colombia, the United States, Ecuador, Spain, and other countries."
    ],
    "tags": [
      "terremoto",
      "ayuda",
      "acopios",
      "mapa"
    ],
    "use_when_label": "Úsalo para encontrar el centro de acopio más cercano donde llevar alimentos, medicinas, ropa o agua.",
    "warning_label": "",
    "category_label": "Mapa",
    "purpose_label": "Ayuda y actualizaciones",
    "status_label": "Activa",
    "operator_type_label": "Voluntario",
    "coverage_label": "Nacional",
    "language_label": "Español",
    "requires_login_label": "No",
    "accepts_reports_label_value": "Sí",
    "public_search_label_value": "Sí",
    "report_found_label_value": "No",
    "owner_label": "Iniciativa voluntaria",
    "service_labels": [
      "Recursos de ayuda"
    ],
    "last_checked_label": "2026-06-26",
    "public_contact_label": "No revisado",
    "api_url_label": "No revisado",
    "source_code_url_label": "No revisado"
  },
  {
    "slug": "copernicus-ems-emsr884",
    "section": "developer",
    "name": "Copernicus EMS Damage Maps (EMSR884)",
    "url": "https://mapping.emergency.copernicus.eu/activations/EMSR884/reporting/",
    "category": "map",
    "purpose": "context-and-location",
    "coverage": "national",
    "language": "en",
    "requires_login": false,
    "last_checked_at": "2026-06-26",
    "owner": "Copernicus EMS",
    "operator_type": "official",
    "status": "active",
    "crawler_priority": 2,
    "accepts_new_reports": false,
    "public_search": true,
    "report_found": false,
    "public_contact": null,
    "services": [
      "damage-reports",
      "situation-updates"
    ],
    "summary": "Activación oficial de cartografía rápida por satélite de Copernicus EMS para el terremoto de Venezuela de 2026: mapas de evaluación de daños y datos geoespaciales para equipos de respuesta, periodistas y analistas.",
    "use_when": {
      "es": "Úsalo para consultar mapas oficiales de daños por satélite y datos geoespaciales del terremoto.",
      "en": "Use this for official satellite damage maps and geospatial data of the earthquake."
    },
    "notes": [
      "Activación EMSR884 del servicio de cartografía rápida de Copernicus EMS, solicitada para el terremoto del 24 de junio de 2026.",
      "Ofrece productos de delineación y gradación de daños como mapas PDF y datos SIG; no tiene búsqueda de personas ni restablecimiento de contacto."
    ],
    "tags": [
      "terremoto",
      "mapa",
      "danos",
      "oficial"
    ],
    "use_when_label": "Úsalo para consultar mapas oficiales de daños por satélite y datos geoespaciales del terremoto.",
    "warning_label": "",
    "category_label": "Mapa",
    "purpose_label": "Contexto y ubicación",
    "status_label": "Activa",
    "operator_type_label": "Oficial",
    "coverage_label": "Nacional",
    "language_label": "Inglés",
    "requires_login_label": "No",
    "accepts_reports_label_value": "No",
    "public_search_label_value": "Sí",
    "report_found_label_value": "No",
    "owner_label": "Copernicus EMS",
    "service_labels": [
      "Reportes de daños",
      "Actualizaciones de situación"
    ],
    "last_checked_label": "2026-06-26",
    "public_contact_label": "No revisado",
    "api_url_label": "No revisado",
    "source_code_url_label": "No revisado"
  },
  {
    "slug": "sismo-venezuela",
    "section": "developer",
    "name": "Sismo Venezuela",
    "url": "https://sismovenezuela.org/",
    "category": "map",
    "purpose": "context-and-location",
    "coverage": "national",
    "language": "es",
    "requires_login": false,
    "last_checked_at": "2026-06-26",
    "owner": "Volunteer initiative",
    "operator_type": "citizen",
    "status": "active",
    "crawler_priority": 2,
    "accepts_new_reports": true,
    "public_search": true,
    "report_found": false,
    "public_contact": null,
    "services": [
      "damage-reports",
      "situation-updates"
    ],
    "summary": "Real-time collaborative map of buildings damaged by the earthquake across Venezuela (Caracas, La Guaira, and nationwide), where people report damage and find nearby aid centers.",
    "use_when": {
      "es": "Úsalo para reportar o consultar edificios dañados y encontrar centros de ayuda cercanos.",
      "en": "Use this to report or check damaged buildings and find nearby aid centers."
    },
    "notes": [
      "URL loaded successfully during the June 26, 2026 link check.",
      "Open citizen map; reports are crowd-sourced and not independently verified."
    ],
    "tags": [
      "terremoto",
      "mapa",
      "danos",
      "comunidad"
    ],
    "use_when_label": "Úsalo para reportar o consultar edificios dañados y encontrar centros de ayuda cercanos.",
    "warning_label": "",
    "category_label": "Mapa",
    "purpose_label": "Contexto y ubicación",
    "status_label": "Activa",
    "operator_type_label": "Ciudadano",
    "coverage_label": "Nacional",
    "language_label": "Español",
    "requires_login_label": "No",
    "accepts_reports_label_value": "Sí",
    "public_search_label_value": "Sí",
    "report_found_label_value": "No",
    "owner_label": "Iniciativa voluntaria",
    "service_labels": [
      "Reportes de daños",
      "Actualizaciones de situación"
    ],
    "last_checked_label": "2026-06-26",
    "public_contact_label": "No revisado",
    "api_url_label": "No revisado",
    "source_code_url_label": "No revisado"
  }
]
